hdhr_disk_space_monitor/__about__.py
hdhr_disk_space_monitor/__init__.py
hdhr_disk_space_monitor/const.py
hdhr_disk_space_monitor/core.py
hdhr_disk_space_monitor/settings.py
hdhr_disk_space_monitor/util.py
hdhr_disk_space_monitor/hdhr/__init__.py
hdhr_disk_space_monitor/hdhr/crc32c.py
hdhr_disk_space_monitor/hdhr/devices.py
hdhr_disk_space_monitor/hdhr/errors.py
hdhr_disk_space_monitor/hdhr/recordings.py
hdhr_disk_space_monitor/hdhr/netif/__init__.py
hdhr_disk_space_monitor/hdhr/netif/getifaddrs.py
hdhr_disk_space_monitor/hdhr/netif/ipconfig.py
hdhr_disk_space_monitor-2.3.0.data/data/share/hdhr_disk_space_monitor/hdhr-disk-space-monitor.service
hdhr_disk_space_monitor-2.3.0.data/data/share/hdhr_disk_space_monitor/hdhr_disk_space_monitor.conf.example
hdhr_disk_space_monitor-2.3.0.dist-info/licenses/LICENSE.txt
tests/__init__.py
tests/test_hdhr_monitor_disk_space.py
hdhr_disk_space_monitor-2.3.0.dist-info/METADATA
hdhr_disk_space_monitor-2.3.0.dist-info/WHEEL
hdhr_disk_space_monitor-2.3.0.dist-info/entry_points.txt
hdhr_disk_space_monitor-2.3.0.dist-info/top_level.txt
hdhr_disk_space_monitor-2.3.0.dist-info/RECORD
