Metadata-Version: 2.4
Name: hdhr_disk_space_monitor
Version: 2.3.0
Summary: Monitor disk space utilization of HDHomeRun SCRIBE, SERVIO, and RECORD devices. Optionally delete recordings to stay above a specified free space minimum, get rid of recordings older than a maximum age, or keep only a certain number of episodes.
Home-page: https://github.com/jmattroberts/hdhr-disk-space-monitor
Author: J. Matt Roberts
Author-email: hdhr.disk.space.monitor@gmail.com
License: GPLv2+
Platform: any
Classifier: Programming Language :: Python :: 3
Classifier: License :: OSI Approved :: GNU General Public License v2 or later (GPLv2+)
Classifier: Operating System :: OS Independent
License-File: LICENSE.txt
Requires-Dist: requests
Requires-Dist: rich
Dynamic: author
Dynamic: author-email
Dynamic: classifier
Dynamic: description
Dynamic: description-content-type
Dynamic: home-page
Dynamic: license
Dynamic: license-file
Dynamic: platform
Dynamic: requires-dist
Dynamic: summary
